{
  "questions": [
    {
      "id": "FGV_PTNA_006",
      "subject": "Informática",
      "topic": "Segurança Digital",
      "difficulty": "Médio",
      "question": "O que é Phishing?",
      "alternatives": {
        "A": "Tipo de vírus que danifica arquivos",
        "B": "Técnica de engenharia social para roubar informações",
        "C": "Tipo de ataque de negação de serviço",
        "D": "Método de criptografia de dados",
        "E": "Tipo de malware que rouba credenciais"
      },
      "answer": "B",
      "explanation": "Phishing é uma técnica de engenharia social que usa mensagens fraudulentas para enganar as pessoas e roubar informações sensíveis como senhas e dados bancários."
    },
    {
      "id": "FGV_PTNA_001",
      "subject": "Informática",
      "topic": "Hardware",
      "difficulty": "Fácil",
      "question": "Qual tipo de memória é volátil e perde seu conteúdo quando o computador é desligado?",
      "alternatives": {
        "A": "Memória ROM",
        "B": "Memória Cache",
        "C": "Memória RAM",
        "D": "Memória SSD",
        "E": "Memória HD"
      },
      "answer": "C",
      "explanation": "A Memória RAM (Random Access Memory) é volátil, ou seja, perde seu conteúdo quando o computador é desligado."
    },
    {
      "id": "FGV_PTNA_013",
      "subject": "Concurso",
      "topic": "Informações Gerais",
      "difficulty": "Fácil",
      "question": "Qual é o órgão responsável pela organização do concurso para PTNA?",
      "alternatives": {
        "A": "Infraero",
        "B": "NAV Brasil",
        "C": "Fundação Getulio Vargas (FGV)",
        "D": "Ministério da Defesa",
        "E": "Comando da Aeronáutica"
      },
      "answer": "C",
      "explanation": "O concurso para o cargo de Profissional Técnico de Navegação Aérea é organizado pela Fundação Getulio Vargas (FGV)."
    },
    {
      "id": "FGV_PTNA_001",
      "subject": "Legislação e Noções de Ética",
      "topic": "NAV Brasil",
      "difficulty": "Fácil",
      "question": "Qual lei criou a NAV Brasil Serviços de Navegação Aérea S.A.?",
      "alternatives": {
        "A": "Lei nº 13.903/2019",
        "B": "Lei nº 14.023/2020",
        "C": "Lei nº 12.123/2019",
        "D": "Lei nº 13.504/2018",
        "E": "Lei nº 14.123/2021"
      },
      "answer": "A",
      "explanation": "A NAV Brasil foi criada pela Lei nº 13.903/2019, que segregou os serviços de navegação aérea da Infraero."
    },
    {
      "id": "FGV_PTNA_004",
      "subject": "Informática",
      "topic": "Software",
      "difficulty": "Fácil",
      "question": "Qual é a função principal do sistema operacional?",
      "alternatives": {
        "A": "Criar documentos",
        "B": "Fazer o intermédio entre o hardware e os programas",
        "C": "Conectar à internet",
        "D": "Processar dados gráficos",
        "E": "Armazenar arquivos"
      },
      "answer": "B",
      "explanation": "O sistema operacional faz o intermédio entre os componentes físicos (hardware) e os programas (software), permitindo que os programas usem o hardware."
    },
    {
      "id": "FGV_PTNA_004",
      "subject": "Informática",
      "topic": "Microsoft 365",
      "difficulty": "Fácil",
      "question": "Qual aplicativo do Microsoft 365 é utilizado para criar e editar planilhas?",
      "alternatives": {
        "A": "Microsoft Word",
        "B": "Microsoft Excel",
        "C": "Microsoft PowerPoint",
        "D": "Microsoft Outlook",
        "E": "Microsoft Teams"
      },
      "answer": "B",
      "explanation": "O Microsoft Excel é o aplicativo do Microsoft 365 específico para criação e edição de planilhas, com fórmulas e gráficos."
    },
    {
      "id": "FGV_PTNA_001",
      "subject": "Raciocínio Lógico Matemático",
      "topic": "Números",
      "difficulty": "Médio",
      "question": "Qual conjunto inclui todos os números inteiros, racionais e irracionais?",
      "alternatives": {
        "A": "N (naturais)",
        "B": "Z (inteiros)",
        "C": "Q (racionais)",
        "D": "I (irracionais)",
        "E": "R (reais)"
      },
      "answer": "E",
      "explanation": "O conjunto dos números reais (R) inclui todos os números inteiros, racionais e irracionais."
    },
    {
      "id": "FGV_PTNA_001",
      "subject": "Raciocínio Lógico Matemático",
      "topic": "Conjuntos",
      "difficulty": "Fácil",
      "question": "Qual símbolo representa 'pertence' na teoria dos conjuntos?",
      "alternatives": {
        "A": "∉",
        "B": "⊂",
        "C": "∈",
        "D": "⊃",
        "E": "∅"
      },
      "answer": "C",
      "explanation": "O símbolo ∈ representa 'pertence' na teoria dos conjuntos, indicando que um elemento faz parte de um conjunto."
    },
    {
      "id": "FGV_PTNA_001",
      "subject": "Língua Portuguesa",
      "topic": "Gramática",
      "difficulty": "Fácil",
      "question": "Qual das alternativas apresenta uma palavra com acentuação gráfica correta?",
      "alternatives": {
        "A": "aviao",
        "B": "cafe",
        "C": "voce",
        "D": "pássaro",
        "E": "ideia"
      },
      "answer": "D",
      "explanation": "A palavra 'pássaro' está corretamente acentuada por ser oxítona terminada em 'o'."
    },
    {
      "id": "FGV_PTNA_001",
      "subject": "Língua Inglesa",
      "topic": "Vocabulário",
      "difficulty": "Fácil",
      "question": "Qual a tradução correta de 'air traffic control'?",
      "alternatives": {
        "A": "Controle de tráfego aéreo",
        "B": "Controle de ar puro",
        "C": "Tráfego aéreo de controle",
        "D": "Controle de tráfego do ar",
        "E": "Ar de controle de tráfego"
      },
      "answer": "A",
      "explanation": "'Air traffic control' traduz-se para 'controle de tráfego aéreo' em português."
    },
    {
      "id": "FGV_PTNA_001",
      "subject": "Informática",
      "topic": "Hardware",
      "difficulty": "Médio",
      "question": "Qual componente é responsável por converter corrente alternada (AC) em corrente contínua (DC)?",
      "alternatives": {
        "A": "CPU",
        "B": "Fonte de alimentação",
        "C": "Placa-mãe",
        "D": "Cooler",
        "E": "Barramento"
      },
      "answer": "B",
      "explanation": "A fonte de alimentação é responsável por converter a corrente alternada (AC) da tomada em corrente contínua (DC) utilizada pelos componentes do computador."
    },
    {
      "id": "FGV_PTNA_013",
      "subject": "Concurso",
      "topic": "Cargo",
      "difficulty": "Fácil",
      "question": "Qual é a escolaridade mínima exigida para o cargo de PTNA?",
      "alternatives": {
        "A": "Ensino Fundamental",
        "B": "Ensino Médio",
        "C": "Ensino Técnico",
        "D": "Ensino Superior",
        "E": "Pós-graduação"
      },
      "answer": "B",
      "explanation": "O cargo de Profissional Técnico de Navegação Aérea (PTNA) exige nível médio de escolaridade."
    },
    {
      "id": "FGV_PTNA_001",
      "subject": "Língua Portuguesa",
      "topic": "Pontuação",
      "difficulty": "Médio",
      "question": "Qual é a função principal da vírgula na frase?",
      "alternatives": {
        "A": "Separar orações coordenadas assindéticas",
        "B": "Indicar pausa na leitura",
        "C": "Separar sujeito e predicado",
        "D": "Marcar o início de uma citação",
        "E": "Separar elementos em uma enumeração"
      },
      "answer": "B",
      "explanation": "A vírgula é usada principalmente para indicar pausa na leitura e separar elementos dentro da frase."
    },
    {
      "id": "FGV_PTNA_001",
      "subject": "Informática",
      "topic": "Hardware",
      "difficulty": "Fácil",
      "question": "Qual componente é considerado o 'cérebro' do computador?",
      "alternatives": {
        "A": "Placa-mãe",
        "B": "Memória RAM",
        "C": "CPU (Processador)",
        "D": "Fonte de alimentação",
        "E": "Placa de vídeo"
      },
      "answer": "C",
      "explanation": "A CPU (Unidade Central de Processamento) é responsável por processar cálculos e executar instruções, sendo considerada o cérebro do computador."
    },
    {
      "id": "FGV_PTNA_015",
      "subject": "Língua Portuguesa",
      "topic": "Morfologia",
      "difficulty": "Médio",
      "question": "Qual das palavras abaixo é um substantivo abstrato?",
      "alternatives": {
        "A": "casa",
        "B": "livro",
        "C": "liberdade",
        "D": "mesa",
        "E": "cadeira"
      },
      "answer": "C",
      "explanation": "'Liberdade' é um substantivo abstrato porque representa uma ideia, algo que não pode ser percebido pelos sentidos."
    },
    {
      "id": "FGV_PTNA_016",
      "subject": "Língua Portuguesa",
      "topic": "Sintaxe",
      "difficulty": "Fácil",
      "question": "Na frase 'O menino brincou no parque', qual é o sujeito da oração?",
      "alternatives": {
        "A": "menino",
        "B": "brincou",
        "C": "no parque",
        "D": "O menino",
        "E": "no"
      },
      "answer": "D",
      "explanation": "O sujeito da oração é 'O menino', que é quem pratica a ação do verbo 'brincou'."
    },
    {
      "id": "FGV_PTNA_017",
      "subject": "Raciocínio Lógico Matemático",
      "topic": "Lógica",
      "difficulty": "Médio",
      "question": "Se todos os A são B, e alguns B são C, o que podemos concluir?",
      "alternatives": {
        "A": "Todos os A são C",
        "B": "Nenhum A é C",
        "C": "Alguns A podem ser C",
        "D": "Não podemos concluir nada",
        "E": "Nenhuma das alternativas"
      },
      "answer": "D",
      "explanation": "Com as informações dadas, não podemos concluir com certeza se alguns A são C ou não, pois a relação não é direta."
    },
    {
      "id": "FGV_PTNA_018",
      "subject": "Raciocínio Lógico Matemático",
      "topic": "Porcentagem",
      "difficulty": "Fácil",
      "question": "Um produto que custava R$ 100,00 teve um aumento de 20%. Qual o novo preço?",
      "alternatives": {
        "A": "R$ 80,00",
        "B": "R$ 100,00",
        "C": "R$ 120,00",
        "D": "R$ 140,00",
        "E": "R$ 200,00"
      },
      "answer": "C",
      "explanation": "20% de R$ 100,00 é R$ 20,00. O novo preço é R$ 100,00 + R$ 20,00 = R$ 120,00."
    },
    {
      "id": "FGV_PTNA_019",
      "subject": "Informática",
      "topic": "Internet",
      "difficulty": "Fácil",
      "question": "O que é um URL?",
      "alternatives": {
        "A": "Unified Resource Locator",
        "B": "Uniform Resource Locator",
        "C": "Universal Resource Locator",
        "D": "Unified Resource Link",
        "E": "Universal Resource Link"
      },
      "answer": "B",
      "explanation": "URL significa Uniform Resource Locator, que é o endereço de um recurso na internet."
    },
    {
      "id": "FGV_PTNA_020",
      "subject": "Informática",
      "topic": "Microsoft Word",
      "difficulty": "Fácil",
      "question": "Qual é o atalho de teclado para colar texto no Microsoft Word?",
      "alternatives": {
        "A": "Ctrl + C",
        "B": "Ctrl + X",
        "C": "Ctrl + V",
        "D": "Ctrl + Z",
        "E": "Ctrl + S"
      },
      "answer": "C",
      "explanation": "Ctrl + V é o atalho para colar texto na maioria dos editores de texto, incluindo Microsoft Word."
    },
    {
      "id": "FGV_PTNA_021",
      "subject": "Legislação e Noções de Ética",
      "topic": "Ética",
      "difficulty": "Médio",
      "question": "Qual o princípio ético que consiste em tratar todos com igualdade e justiça?",
      "alternatives": {
        "A": "Imparcialidade",
        "B": "Integridade",
        "C": "Lealdade",
        "D": "Transparência",
        "E": "Responsabilidade"
      },
      "answer": "A",
      "explanation": "A imparcialidade é o princípio de tratar todas as pessoas com igualdade, sem favorecer ou prejudicar ninguém."
    },
    {
      "id": "FGV_PTNA_022",
      "subject": "Legislação e Noções de Ética",
      "topic": "NAV Brasil",
      "difficulty": "Fácil",
      "question": "A NAV Brasil está vinculada a qual ministério?",
      "alternatives": {
        "A": "Ministério das Comunicações",
        "B": "Ministério da Defesa",
        "C": "Ministério da Infraestrutura",
        "D": "Ministério da Justiça",
        "E": "Ministério da Economia"
      },
      "answer": "B",
      "explanation": "A NAV Brasil está vinculada ao Ministério da Defesa por intermédio do Comando da Aeronáutica."
    },
    {
      "id": "FGV_PTNA_023",
      "subject": "Língua Inglesa",
      "topic": "Vocabulário",
      "difficulty": "Fácil",
      "question": "Qual a tradução de 'navigation'?",
      "alternatives": {
        "A": "Navegação",
        "B": "Navegador",
        "C": "Navegar",
        "D": "Nave",
        "E": "Naufrágio"
      },
      "answer": "A",
      "explanation": "'Navigation' traduz-se para 'navegação' em português."
    },
    {
      "id": "FGV_PTNA_024",
      "subject": "Língua Inglesa",
      "topic": "Gramática",
      "difficulty": "Fácil",
      "question": "Qual o tempo verbal presente do verbo 'to be' na 3ª pessoa do singular?",
      "alternatives": {
        "A": "am",
        "B": "is",
        "C": "are",
        "D": "be",
        "E": "been"
      },
      "answer": "B",
      "explanation": "Na 3ª pessoa do singular, o verbo 'to be' no presente é 'is'."
    },
    {
      "id": "FGV_PTNA_025",
      "subject": "Navegação Aérea",
      "topic": "Controle de Tráfego",
      "difficulty": "Médio",
      "question": "O que é 'separação de tráfego' na aviação?",
      "alternatives": {
        "A": "Separação entre aeronaves e terreno",
        "B": "Manter distância segura entre aeronaves",
        "C": "Separação entre diferentes tipos de aeronaves",
        "D": "Separação horizontal e vertical",
        "E": "Todas as alternativas"
      },
      "answer": "E",
      "explanation": "A separação de tráfego envolve manter distâncias seguras entre aeronaves, separação de aeronaves com terreno, e separação horizontal e vertical."
    },
    {
      "id": "FGV_PTNA_026",
      "subject": "Navegação Aérea",
      "topic": "Espaço Aéreo",
      "difficulty": "Fácil",
      "question": "Quem é responsável pela prestação do serviço de controle de tráfego aéreo no Brasil?",
      "alternatives": {
        "A": "Infraero",
        "B": "DECEA",
        "C": "NAV Brasil",
        "D": "ANAC",
        "E": "FAB"
      },
      "answer": "C",
      "explanation": "A NAV Brasil é responsável pela prestação do serviço de controle de tráfego aéreo no Brasil após a separação da Infraero."
    }
  ],
  "total": 26,
  "subjects": [
    "Língua Portuguesa",
    "Concurso",
    "Raciocínio Lógico Matemático",
    "Língua Inglesa",
    "Informática",
    "Legislação e Noções de Ética",
    "Navegação Aérea"
  ]
}