[
    {
        "id": "2034578",
        "enunciado": "Foram compradas 216 poltronas novas para o auditório de uma repartição pública, cada poltrona vai ter também uma capa de proteção, estas capas são vendidas em caixas que contém exatamente uma dúzia. Desta forma, para que todas as poltronas tenham uma capa, o total de caixas compradas deve ser igual a:",
        "alternativas": {
            "A": "12.",
            "B": "16.",
            "C": "18.",
            "D": "20.",
            "E": "22."
        },
        "gabarito_correto": "C",
        "comentario_ia": "Cada capa é vendida em uma caixa com 12 unidades. Para cobrir 216 poltronas, são necessárias 216 poltronas / 12 capas/caixa = 18 caixas."
    },
    {
        "id": "2121114",
        "enunciado": "Para higienizar os moldes de aparelhos auditivos de um lote de 273 pacientes, foram utilizados frascos de solução com capacidade de 225 mL. Sabendo-se que o total utilizado foi de 40.950 mL, quantos frascos foram consumidos?",
        "alternativas": {
            "A": "193.",
            "B": "182.",
            "C": "207.",
            "D": "219."
        },
        "gabarito_correto": "B",
        "comentario_ia": "Para encontrar o numero de frascos consumidos, divida o total de volume utilizado pela capacidade de cada frasco: 40.950 mL / 225 mL = 182 frascos. Portanto, foram consumidos 182 frascos."
    },
    {
        "id": "2285676",
        "enunciado": "O custo total para elaborar certo conjunto de questões foi de R$ 3.750,00, dividido igualmente entre 12 professores. Qual o valor pago a cada professor?",
        "alternativas": {
            "A": "R$ 300,00.",
            "B": "R$ 340,00.",
            "C": "R$ 312,50.",
            "D": "R$ 295,50."
        },
        "gabarito_correto": "C",
        "comentario_ia": "Para encontrar o valor pago a cada professor, divide-se o custo total pelo número de professores: R$ 3.750,00 / 12 = R$ 312,50."
    },
    {
        "id": "2112570",
        "enunciado": "Os         120         alunos         do         4º         ano         de         uma         escola         realizarão         um\npasseio.         Para         isso,         eles         serão         distribuídos         igualmente\nentre         4         ônibus.         Qual         a         quantidade         de         alunos         irá         em         cada\nônibus?         Assinale         a         alternativa         correta:",
        "alternativas": {
            "A": "28         alunos.",
            "B": "45         alunos.",
            "C": "40         alunos.",
            "D": "35         alunos.",
            "E": "30         alunos."
        },
        "gabarito_correto": "E",
        "comentario_ia": "Para determinar a quantidade de alunos por ônibus, basta dividir o número total de alunos pelo número de ônibus: 120 alunos / 4 ônibus = 30 alunos por ônibus."
    },
    {
        "id": "2384113",
        "enunciado": "Um centro de distribuiçªo recebeu 840 pacotes, que precisaram ser organizados igualmente em 12 caminhıes. Quantos pacotes foram colocados em cada caminhªo?",
        "alternativas": {
            "A": "65",
            "B": "68",
            "C": "70",
            "D": "72",
            "E": "75"
        },
        "gabarito_correto": "C",
        "comentario_ia": "Para distribuir igualmente os pacotes, divide-se o total de pacotes pelo número de caminhões: 840 ÷ 12 = 70 pacotes por caminhão."
    },
    {
        "id": "2071077",
        "enunciado": "Para a festinha de confraternização dos funcionários de uma empresa foi feito o orçamento de R$ 488,40. Os 8 funcionários dessa empresa combinaram dividir igualmente entre eles esse valor. A quantia que caberá a cada um deles é:",
        "alternativas": {
            "A": "R$ 41,05",
            "B": "R$ 60,00",
            "C": "R$ 68,00",
            "D": "R$ 61,05",
            "E": "R$ 61,50"
        },
        "gabarito_correto": "D",
        "comentario_ia": "Para encontrar a quantia que caberá a cada funcionário, basta dividir o orçamento total pelo número de funcionários: R$ 488,40 / 8 = R$ 61,05. Assim, cada um pagará R$ 61,05."
    },
    {
        "id": "2172159",
        "enunciado": "Uma empresa recebeu um pedido para entregar 864 garrafas de água. Essas garrafas foram colocadas em caixas com 36 garrafas em cada caixa. Quantas caixas foram necessárias para transportar todas as garrafas?",
        "alternativas": {
            "A": "22 ;",
            "B": "24 ;",
            "C": "26 ;",
            "D": "28 ."
        },
        "gabarito_correto": "B",
        "comentario_ia": "Para encontrar o número de caixas, divide-se o total de garrafas pelo número de garrafas por caixa: 864 / 36. A divisão resulta em 24, indicando que 24 caixas foram necessárias."
    },
    {
        "id": "2315614",
        "enunciado": "Assinale a alternativa que apresenta o quociente da seguinte divisão: 518,91 ÷ 35,3",
        "alternativas": {
            "A": "483,61.",
            "B": "14,7.",
            "C": "15,5.",
            "D": "24,7."
        },
        "gabarito_correto": "B",
        "comentario_ia": "Para encontrar o quociente, dividimos 518,91 por 35,3. O resultado aproximado é 14,7. 518,91 / 35,3 = 14,7. Portanto, a alternativa B é a correta."
    },
    {
        "id": "2374588",
        "enunciado": "Um carpinteiro dispõe de um pedaço de madeira com 54 centímetros de comprimento. Ele precisa cortar essa madeira em 12 pedaços menores de igual comprimento, para usar em pequenos consertos que faz diariamente. O tamanho de cada um desses pedaços menores, em centímetros, obtido por esse carpinteiro será:",
        "alternativas": {
            "A": "0,045",
            "B": "0,45",
            "C": "4,5",
            "D": "45",
            "E": "450"
        },
        "gabarito_correto": "C",
        "comentario_ia": "Para obter 12 pedaços de igual comprimento a partir de 54 cm, faz-se a divisão: 54 cm / 12 = 4,5 cm. Cada pedaço terá 4,5 centímetros."
    },
    {
        "id": "2346906",
        "enunciado": "Nestor precisa distribuir 144 litros de desinfetante igualmente entre 9 escolas da cidade. Quantos litros do produto cada escola receberá?",
        "alternativas": {
            "A": "14.",
            "B": "15.",
            "C": "16.",
            "D": "17.",
            "E": "18."
        },
        "gabarito_correto": "C",
        "comentario_ia": "Para saber quantos litros cada escola receberá, basta dividir o total de litros de desinfetante pelo número de escolas: 144 litros / 9 escolas = 16 litros por escola."
    },
    {
        "id": "2323472",
        "enunciado": "Durante a preparação para um concurso público, Pietra decidiu estudar 420 questões em 14 dias, dividindo a quantidade igualmente entre os dias da semana. Quantas questões Pietra resolveu por dia?",
        "alternativas": {
            "A": "30",
            "B": "28",
            "C": "29",
            "D": "32",
            "E": "35"
        },
        "gabarito_correto": "A",
        "comentario_ia": "Para saber quantas questões Pietra resolveu por dia, dividimos o total de questões (420) pelo número de dias (14): 420 ÷ 14 = 30 questões por dia."
    },
    {
        "id": "2310191",
        "enunciado": "Em uma comemoração na escola, Mateus ficou responsável por montar as lembrancinhas para seus colegas. Para isso, ele levou 120 balas e decidiu colocá-las em 6 potes de plástico transparente, que seriam distribuídos ao final da festa. Como Mateus queria que todos os potes ficassem com a mesma quantidade de balas, ele resolveu dividir os 120 doces de forma igualitária entre os 6 potes. Quantas balas foram colocadas em cada pote?",
        "alternativas": {
            "A": "20",
            "B": "18",
            "C": "21",
            "D": "22",
            "E": "25"
        },
        "gabarito_correto": "A",
        "comentario_ia": "Para saber quantas balas foram colocadas em cada pote, basta dividir o total de balas (120) pelo número de potes (6). A divisão 120 ÷ 6 resulta em 20. Portanto, cada pote recebeu 20 balas."
    },
    {
        "id": "2376308",
        "enunciado": "Uma caixa contØm 216 bombons que serªo divididos igualmente em 8 saquinhos. Quantos bombons terÆ cada saquinho:",
        "alternativas": {
            "A": "25 bombons.",
            "B": "26 bombons.",
            "C": "27 bombons.",
            "D": "28 bombons.",
            "E": "29 bombons."
        },
        "gabarito_correto": "C",
        "comentario_ia": "Para distribuir os bombons igualmente, divide-se o total de bombons pelo número de saquinhos. 216 bombons / 8 saquinhos = 27 bombons por saquinho."
    },
    {
        "id": "2376310",
        "enunciado": "Na sala de aula hÆ 32 alunos. A professora organizou as carteiras em 4 fileiras com a mesma quantidade de alunos em cada uma. Quantos alunos ficaram em cada fileira:",
        "alternativas": {
            "A": "7 alunos.",
            "B": "8 alunos.",
            "C": "9 alunos.",
            "D": "10 alunos.",
            "E": "12 alunos."
        },
        "gabarito_correto": "B",
        "comentario_ia": "Para saber quantos alunos ficaram em cada fileira, divide-se o total de alunos pelo número de fileiras. 32 alunos / 4 fileiras = 8 alunos por fileira."
    },
    {
        "id": "2396398",
        "enunciado": "Lúcio tem 8580 panfletos para distribuir de maneira igual durante os 30 dias do mês. Assinale a alternativa que apresenta quantos panfletos ele distribuirá por dia.",
        "alternativas": {
            "A": "262 panfletos",
            "B": "275 panfletos",
            "C": "280 panfletos",
            "D": "286 panfletos",
            "E": "300 panfletos"
        },
        "gabarito_correto": "D",
        "comentario_ia": "Para encontrar quantos panfletos Lúcio distribuirá por dia, basta dividir o total de panfletos pelo número de dias: 8580 panfletos / 30 dias. O resultado exato dessa divisão é 286 panfletos por dia. Portanto, a alternativa D está correta."
    },
    {
        "id": "2159632",
        "enunciado": "Fabiano juntou R$ 1.000,00 em moedas de R$ 1,00. Ele trocou todo esse valor por cédulas de R$ 50,00. Quantas cédulas de R$50,00 Fabiano recebeu após a troca?",
        "alternativas": {
            "A": "15",
            "B": "18",
            "C": "20",
            "D": "25",
            "E": "Nenhuma das alternativas"
        },
        "gabarito_correto": "C",
        "comentario_ia": "Fabiano tinha R$ 1.000,00 em moedas de R$ 1,00. Ao trocar por cédulas de R$ 50,00, basta dividir o valor total pelo valor da cédula: R$ 1.000,00 / R$ 50,00 = 20 cédulas."
    },
    {
        "id": "2324099",
        "enunciado": "Durante um piquenique com seus colegas, Isabela levou 96 docinhos para compartilhar igualmente entre 8 cestas de lanche. Quantos docinhos foram colocados em cada cesta?",
        "alternativas": {
            "A": "10",
            "B": "11",
            "C": "17",
            "D": "12",
            "E": "14"
        },
        "gabarito_correto": "D",
        "comentario_ia": "Para saber quantos docinhos foram colocados em cada cesta, basta dividir o total de docinhos pelo número de cestas: 96 docinhos / 8 cestas = 12 docinhos por cesta."
    },
    {
        "id": "2324018",
        "enunciado": "Durante um concurso de culinária, Daiane preparou 120 mini bolos para apresentar à banca avaliadora. Ela decidiu distribuir os doces igualmente em 10 bandejas para a exposição. Quantos mini bolos Daiane colocou em cada bandeja?",
        "alternativas": {
            "A": "10",
            "B": "11",
            "C": "12",
            "D": "13",
            "E": "14"
        },
        "gabarito_correto": "C",
        "comentario_ia": "Para calcular quantos mini bolos cabem em cada bandeja, basta dividir o total de mini bolos pelo número de bandejas. 120 mini bolos / 10 bandejas = 12 mini bolos por bandeja. A alternativa C está correta."
    },
    {
        "id": "2159644",
        "enunciado": "Marina organizou uma festa de aniversário para seus sobrinhos e recebeu como presente uma caixa com 144 balas para distribuir entre eles. Ela decidiu dividir essas balas de forma igualitária entre seus 12 sobrinhos, sem sobrar nenhuma bala. Quantas balas cada sobrinho recebeu?",
        "alternativas": {
            "A": "10",
            "B": "11",
            "C": "12",
            "D": "13",
            "E": "14"
        },
        "gabarito_correto": "C",
        "comentario_ia": "Para dividir as balas igualmente, basta dividir o número total de balas pelo número de sobrinhos. 144 balas / 12 sobrinhos = 12 balas por sobrinho."
    },
    {
        "id": "2384081",
        "enunciado": "Um estacionamento organizou os carros em 4 fileiras, colocando a mesma quantidade de carros em cada uma. Ao final da organizaçªo, havia 32 carros no total. Quantos carros ficaram em cada fileira?",
        "alternativas": {
            "A": "6",
            "B": "7",
            "C": "4",
            "D": "8",
            "E": "10"
        },
        "gabarito_correto": "D",
        "comentario_ia": "Para saber quantos carros há em cada fileira, dividimos o total de carros (32) pelo número de fileiras (4). 32 ÷ 4 = 8. Portanto, há 8 carros em cada fileira."
    },
    {
        "id": "2158574",
        "enunciado": "Matias tem 48 páginas para ler de um livro. Ele decide ler 6 páginas por dia, todos os dias, sem parar. Quantos dias Matias levará para terminar a leitura?",
        "alternativas": {
            "A": "6",
            "B": "7",
            "C": "8",
            "D": "9",
            "E": "13"
        },
        "gabarito_correto": "C",
        "comentario_ia": "Para calcular o número de dias, divide-se o total de páginas pelo número de páginas lidas por dia. 48 páginas / 6 páginas/dia = 8 dias. Portanto, Matias levará 8 dias para terminar a leitura."
    },
    {
        "id": "2063187",
        "enunciado": "Um cano de esgoto tem 18 metros de comprimento e precisa ser dividido em 4 partes iguais. Qual é o comprimento de cada parte?",
        "alternativas": {
            "A": "3,0 metros",
            "B": "4,5 metros",
            "C": "2,0 metros",
            "D": "5,5 metros"
        },
        "gabarito_correto": "B",
        "comentario_ia": "Para dividir 18 metros em 4 partes iguais, basta realizar a operação 18 / 4, que resulta em 4,5 metros para cada parte."
    },
    {
        "id": "2033611",
        "enunciado": "Um motorista precisa dividir igualmente uma carga de 1500 kg entre 5 caminhões. Quantos quilogramas de carga cada caminhão deverá transportar?",
        "alternativas": {
            "A": "250 kg.",
            "B": "300 kg.",
            "C": "350 kg.",
            "D": "400 kg."
        },
        "gabarito_correto": "B",
        "comentario_ia": "Para dividir igualmente 1500 kg entre 5 caminhões, basta realizar a operação de divisão: 1500 kg / 5 caminhões = 300 kg por caminhão."
    },
    {
        "id": "2199375",
        "enunciado": "Antônio possui 45 livros e pretende organizá-los em 3 prateleiras de modo que todas as prateleiras tenham a mesma quantidade de livros. Portanto, pode-se dizer que a quantidade total de livros em cada prateleira será igual a:",
        "alternativas": {
            "A": "15",
            "B": "14",
            "C": "13",
            "D": "12"
        },
        "gabarito_correto": "A",
        "comentario_ia": "O calculo para determinar a quantidade de livros em cada prateleira consiste em dividir o total de livros (45) pelo numero de prateleiras (3), resultando em 15 livros por prateleira."
    },
    {
        "id": "1011940",
        "enunciado": "Ana comprou 51 chocolates e deseja distribuí-los entre seus 3 netos. Sabendo-se que todos receberão a mesma quantidade, ao todo, quantos chocolates cada neto receberá?",
        "alternativas": {
            "A": "16",
            "B": "17",
            "C": "18",
            "D": "19"
        },
        "gabarito_correto": "B",
        "comentario_ia": "Para saber quantos chocolates cada neto receberá, divida o total de chocolates pelo número de netos. 51 chocolates / 3 netos = 17 chocolates por neto. A divisão resulta em 17, que é a quantidade que cada neto receberá."
    },
    {
        "id": "2046491",
        "enunciado": "Um caminhão possui capacidade de carga de até 5.000 quilos. Qual é o maior número de caixas que ele pode transportar, se cada uma delas pesa 100 quilos?",
        "alternativas": {
            "A": "30.",
            "B": "40.",
            "C": "50.",
            "D": "60."
        },
        "gabarito_correto": "C",
        "comentario_ia": "Para calcular o número máximo de caixas, divida a capacidade total do caminhão pelo peso de cada caixa: 5000 kg / 100 kg/caixa = 50 caixas. Portanto, o caminhão pode transportar 50 caixas."
    },
    {
        "id": "2133749",
        "enunciado": "Gabriel fez um bolo e cortou em 16 fatias. Sabendo-se que ele tem que levar, para a escola, 128 fatias para uma festa, no mínimo, quantos bolos iguais ao anterior ele precisa fazer para conseguir as fatias a fim de levar para a escola?",
        "alternativas": {
            "A": "9",
            "B": "8",
            "C": "7",
            "D": "6"
        },
        "gabarito_correto": "B",
        "comentario_ia": "Para encontrar o número mínimo de bolos, divide-se o total de fatias necessárias (128) pelo número de fatias por bolo (16). 128 / 16 = 8. Portanto, Gabriel precisa fazer no mínimo 8 bolos."
    },
    {
        "id": "1189759",
        "enunciado": "Quatro estudantes de uma turma do ensino fundamental vão dividir igualmente entre eles a despesa que tiveram na compra de material para fazerem um trabalho da escola. Sabendo que o valor total da compra foi R$ 89,76, caberá a cada estudante a quantia de:",
        "alternativas": {
            "A": "R$ 22,44",
            "B": "R$ 21,40",
            "C": "R$ 20,44",
            "D": "R$ 21,45",
            "E": "R$ 20,24"
        },
        "gabarito_correto": "A",
        "comentario_ia": "Para dividir igualmente o valor da compra entre os 4 estudantes, basta dividir o valor total pela quantidade de estudantes. Valor por estudante = R$ 89,76 / 4 = R$ 22,44. A alternativa A apresenta o valor correto."
    },
    {
        "id": "2122664",
        "enunciado": "Se 10 rosas formam dois buquês de flores, é CORRETO afirmar que cada buquê possui exatamente:",
        "alternativas": {
            "A": "4 rosas.",
            "B": "5 rosas.",
            "C": "6 rosas.",
            "D": "10 rosas."
        },
        "gabarito_correto": "B",
        "comentario_ia": "Se 10 rosas formam dois buquês de forma igual, cada buquê terá 10 rosas / 2 buquês = 5 rosas por buquê. Logo, a alternativa B é a correta."
    },
    {
        "id": "1991828",
        "enunciado": "Um senhor combinou com o jornaleiro que pagaria adiantado e receberia sem custos seus jornais em casa. Cada exemplar custa R$ 1,25, o jornaleiro recebeu adiantado R$ 60,00, durante quantos dias o senhor receberá seu jornal em casa?",
        "alternativas": {
            "A": "40 dias.",
            "B": "44 dias.",
            "C": "48 dias.",
            "D": "52 dias."
        },
        "gabarito_correto": "C",
        "comentario_ia": "Para calcular o numero de dias, divida o valor total adiantado (R$ 60,00) pelo custo diario de cada jornal (R$ 1,25). 60,00 / 1,25 = 48. Portanto, o senhor recebera o jornal por 48 dias."
    },
    {
        "id": "2034578",
        "enunciado": "Foram compradas 216 poltronas novas para o auditório de uma repartição pública, cada poltrona vai ter também uma capa de proteção, estas capas são vendidas em caixas que contém exatamente uma dúzia. Desta forma, para que todas as poltronas tenham uma capa, o total de caixas compradas deve ser igual a:",
        "alternativas": {
            "A": "12.",
            "B": "16.",
            "C": "18.",
            "D": "20.",
            "E": "22."
        },
        "gabarito_correto": "C",
        "comentario_ia": "Cada capa é vendida em uma caixa com 12 unidades. Para cobrir 216 poltronas, são necessárias 216 poltronas / 12 capas/caixa = 18 caixas."
    },
    {
        "id": "2121114",
        "enunciado": "Para higienizar os moldes de aparelhos auditivos de um lote de 273 pacientes, foram utilizados frascos de solução com capacidade de 225 mL. Sabendo-se que o total utilizado foi de 40.950 mL, quantos frascos foram consumidos?",
        "alternativas": {
            "A": "193.",
            "B": "182.",
            "C": "207.",
            "D": "219."
        },
        "gabarito_correto": "B",
        "comentario_ia": "Para encontrar o numero de frascos consumidos, divida o total de volume utilizado pela capacidade de cada frasco: 40.950 mL / 225 mL = 182 frascos. Portanto, foram consumidos 182 frascos."
    },
    {
        "id": "2285676",
        "enunciado": "O custo total para elaborar certo conjunto de questões foi de R$ 3.750,00, dividido igualmente entre 12 professores. Qual o valor pago a cada professor?",
        "alternativas": {
            "A": "R$ 300,00.",
            "B": "R$ 340,00.",
            "C": "R$ 312,50.",
            "D": "R$ 295,50."
        },
        "gabarito_correto": "C",
        "comentario_ia": "Para encontrar o valor pago a cada professor, divide-se o custo total pelo número de professores: R$ 3.750,00 / 12 = R$ 312,50."
    },
    {
        "id": "2112570",
        "enunciado": "Os         120         alunos         do         4º         ano         de         uma         escola         realizarão         um\npasseio.         Para         isso,         eles         serão         distribuídos         igualmente\nentre         4         ônibus.         Qual         a         quantidade         de         alunos         irá         em         cada\nônibus?         Assinale         a         alternativa         correta:",
        "alternativas": {
            "A": "28         alunos.",
            "B": "45         alunos.",
            "C": "40         alunos.",
            "D": "35         alunos.",
            "E": "30         alunos."
        },
        "gabarito_correto": "E",
        "comentario_ia": "Para determinar a quantidade de alunos por ônibus, basta dividir o número total de alunos pelo número de ônibus: 120 alunos / 4 ônibus = 30 alunos por ônibus."
    },
    {
        "id": "2384113",
        "enunciado": "Um centro de distribuiçªo recebeu 840 pacotes, que precisaram ser organizados igualmente em 12 caminhıes. Quantos pacotes foram colocados em cada caminhªo?",
        "alternativas": {
            "A": "65",
            "B": "68",
            "C": "70",
            "D": "72",
            "E": "75"
        },
        "gabarito_correto": "C",
        "comentario_ia": "Para distribuir igualmente os pacotes, divide-se o total de pacotes pelo número de caminhões: 840 ÷ 12 = 70 pacotes por caminhão."
    },
    {
        "id": "2071077",
        "enunciado": "Para a festinha de confraternização dos funcionários de uma empresa foi feito o orçamento de R$ 488,40. Os 8 funcionários dessa empresa combinaram dividir igualmente entre eles esse valor. A quantia que caberá a cada um deles é:",
        "alternativas": {
            "A": "R$ 41,05",
            "B": "R$ 60,00",
            "C": "R$ 68,00",
            "D": "R$ 61,05",
            "E": "R$ 61,50"
        },
        "gabarito_correto": "D",
        "comentario_ia": "Para encontrar a quantia que caberá a cada funcionário, basta dividir o orçamento total pelo número de funcionários: R$ 488,40 / 8 = R$ 61,05. Assim, cada um pagará R$ 61,05."
    },
    {
        "id": "2172159",
        "enunciado": "Uma empresa recebeu um pedido para entregar 864 garrafas de água. Essas garrafas foram colocadas em caixas com 36 garrafas em cada caixa. Quantas caixas foram necessárias para transportar todas as garrafas?",
        "alternativas": {
            "A": "22 ;",
            "B": "24 ;",
            "C": "26 ;",
            "D": "28 ."
        },
        "gabarito_correto": "B",
        "comentario_ia": "Para encontrar o número de caixas, divide-se o total de garrafas pelo número de garrafas por caixa: 864 / 36. A divisão resulta em 24, indicando que 24 caixas foram necessárias."
    },
    {
        "id": "2315614",
        "enunciado": "Assinale a alternativa que apresenta o quociente da seguinte divisão: 518,91 ÷ 35,3",
        "alternativas": {
            "A": "483,61.",
            "B": "14,7.",
            "C": "15,5.",
            "D": "24,7."
        },
        "gabarito_correto": "B",
        "comentario_ia": "Para encontrar o quociente, dividimos 518,91 por 35,3. O resultado aproximado é 14,7. 518,91 / 35,3 = 14,7. Portanto, a alternativa B é a correta."
    },
    {
        "id": "2374588",
        "enunciado": "Um carpinteiro dispõe de um pedaço de madeira com 54 centímetros de comprimento. Ele precisa cortar essa madeira em 12 pedaços menores de igual comprimento, para usar em pequenos consertos que faz diariamente. O tamanho de cada um desses pedaços menores, em centímetros, obtido por esse carpinteiro será:",
        "alternativas": {
            "A": "0,045",
            "B": "0,45",
            "C": "4,5",
            "D": "45",
            "E": "450"
        },
        "gabarito_correto": "C",
        "comentario_ia": "Para obter 12 pedaços de igual comprimento a partir de 54 cm, faz-se a divisão: 54 cm / 12 = 4,5 cm. Cada pedaço terá 4,5 centímetros."
    },
    {
        "id": "2346906",
        "enunciado": "Nestor precisa distribuir 144 litros de desinfetante igualmente entre 9 escolas da cidade. Quantos litros do produto cada escola receberá?",
        "alternativas": {
            "A": "14.",
            "B": "15.",
            "C": "16.",
            "D": "17.",
            "E": "18."
        },
        "gabarito_correto": "C",
        "comentario_ia": "Para saber quantos litros cada escola receberá, basta dividir o total de litros de desinfetante pelo número de escolas: 144 litros / 9 escolas = 16 litros por escola."
    },
    {
        "id": "2323472",
        "enunciado": "Durante a preparação para um concurso público, Pietra decidiu estudar 420 questões em 14 dias, dividindo a quantidade igualmente entre os dias da semana. Quantas questões Pietra resolveu por dia?",
        "alternativas": {
            "A": "30",
            "B": "28",
            "C": "29",
            "D": "32",
            "E": "35"
        },
        "gabarito_correto": "A",
        "comentario_ia": "Para saber quantas questões Pietra resolveu por dia, dividimos o total de questões (420) pelo número de dias (14): 420 ÷ 14 = 30 questões por dia."
    },
    {
        "id": "2310191",
        "enunciado": "Em uma comemoração na escola, Mateus ficou responsável por montar as lembrancinhas para seus colegas. Para isso, ele levou 120 balas e decidiu colocá-las em 6 potes de plástico transparente, que seriam distribuídos ao final da festa. Como Mateus queria que todos os potes ficassem com a mesma quantidade de balas, ele resolveu dividir os 120 doces de forma igualitária entre os 6 potes. Quantas balas foram colocadas em cada pote?",
        "alternativas": {
            "A": "20",
            "B": "18",
            "C": "21",
            "D": "22",
            "E": "25"
        },
        "gabarito_correto": "A",
        "comentario_ia": "Para saber quantas balas foram colocadas em cada pote, basta dividir o total de balas (120) pelo número de potes (6). A divisão 120 ÷ 6 resulta em 20. Portanto, cada pote recebeu 20 balas."
    },
    {
        "id": "2376308",
        "enunciado": "Uma caixa contØm 216 bombons que serªo divididos igualmente em 8 saquinhos. Quantos bombons terÆ cada saquinho:",
        "alternativas": {
            "A": "25 bombons.",
            "B": "26 bombons.",
            "C": "27 bombons.",
            "D": "28 bombons.",
            "E": "29 bombons."
        },
        "gabarito_correto": "C",
        "comentario_ia": "Para distribuir os bombons igualmente, divide-se o total de bombons pelo número de saquinhos. 216 bombons / 8 saquinhos = 27 bombons por saquinho."
    },
    {
        "id": "2376310",
        "enunciado": "Na sala de aula hÆ 32 alunos. A professora organizou as carteiras em 4 fileiras com a mesma quantidade de alunos em cada uma. Quantos alunos ficaram em cada fileira:",
        "alternativas": {
            "A": "7 alunos.",
            "B": "8 alunos.",
            "C": "9 alunos.",
            "D": "10 alunos.",
            "E": "12 alunos."
        },
        "gabarito_correto": "B",
        "comentario_ia": "Para saber quantos alunos ficaram em cada fileira, divide-se o total de alunos pelo número de fileiras. 32 alunos / 4 fileiras = 8 alunos por fileira."
    },
    {
        "id": "2396398",
        "enunciado": "Lúcio tem 8580 panfletos para distribuir de maneira igual durante os 30 dias do mês. Assinale a alternativa que apresenta quantos panfletos ele distribuirá por dia.",
        "alternativas": {
            "A": "262 panfletos",
            "B": "275 panfletos",
            "C": "280 panfletos",
            "D": "286 panfletos",
            "E": "300 panfletos"
        },
        "gabarito_correto": "D",
        "comentario_ia": "Para encontrar quantos panfletos Lúcio distribuirá por dia, basta dividir o total de panfletos pelo número de dias: 8580 panfletos / 30 dias. O resultado exato dessa divisão é 286 panfletos por dia. Portanto, a alternativa D está correta."
    },
    {
        "id": "2159632",
        "enunciado": "Fabiano juntou R$ 1.000,00 em moedas de R$ 1,00. Ele trocou todo esse valor por cédulas de R$ 50,00. Quantas cédulas de R$50,00 Fabiano recebeu após a troca?",
        "alternativas": {
            "A": "15",
            "B": "18",
            "C": "20",
            "D": "25",
            "E": "Nenhuma das alternativas"
        },
        "gabarito_correto": "C",
        "comentario_ia": "Fabiano tinha R$ 1.000,00 em moedas de R$ 1,00. Ao trocar por cédulas de R$ 50,00, basta dividir o valor total pelo valor da cédula: R$ 1.000,00 / R$ 50,00 = 20 cédulas."
    },
    {
        "id": "2324099",
        "enunciado": "Durante um piquenique com seus colegas, Isabela levou 96 docinhos para compartilhar igualmente entre 8 cestas de lanche. Quantos docinhos foram colocados em cada cesta?",
        "alternativas": {
            "A": "10",
            "B": "11",
            "C": "17",
            "D": "12",
            "E": "14"
        },
        "gabarito_correto": "D",
        "comentario_ia": "Para saber quantos docinhos foram colocados em cada cesta, basta dividir o total de docinhos pelo número de cestas: 96 docinhos / 8 cestas = 12 docinhos por cesta."
    },
    {
        "id": "2324018",
        "enunciado": "Durante um concurso de culinária, Daiane preparou 120 mini bolos para apresentar à banca avaliadora. Ela decidiu distribuir os doces igualmente em 10 bandejas para a exposição. Quantos mini bolos Daiane colocou em cada bandeja?",
        "alternativas": {
            "A": "10",
            "B": "11",
            "C": "12",
            "D": "13",
            "E": "14"
        },
        "gabarito_correto": "C",
        "comentario_ia": "Para calcular quantos mini bolos cabem em cada bandeja, basta dividir o total de mini bolos pelo número de bandejas. 120 mini bolos / 10 bandejas = 12 mini bolos por bandeja. A alternativa C está correta."
    },
    {
        "id": "2159644",
        "enunciado": "Marina organizou uma festa de aniversário para seus sobrinhos e recebeu como presente uma caixa com 144 balas para distribuir entre eles. Ela decidiu dividir essas balas de forma igualitária entre seus 12 sobrinhos, sem sobrar nenhuma bala. Quantas balas cada sobrinho recebeu?",
        "alternativas": {
            "A": "10",
            "B": "11",
            "C": "12",
            "D": "13",
            "E": "14"
        },
        "gabarito_correto": "C",
        "comentario_ia": "Para dividir as balas igualmente, basta dividir o número total de balas pelo número de sobrinhos. 144 balas / 12 sobrinhos = 12 balas por sobrinho."
    },
    {
        "id": "2384081",
        "enunciado": "Um estacionamento organizou os carros em 4 fileiras, colocando a mesma quantidade de carros em cada uma. Ao final da organizaçªo, havia 32 carros no total. Quantos carros ficaram em cada fileira?",
        "alternativas": {
            "A": "6",
            "B": "7",
            "C": "4",
            "D": "8",
            "E": "10"
        },
        "gabarito_correto": "D",
        "comentario_ia": "Para saber quantos carros há em cada fileira, dividimos o total de carros (32) pelo número de fileiras (4). 32 ÷ 4 = 8. Portanto, há 8 carros em cada fileira."
    },
    {
        "id": "2158574",
        "enunciado": "Matias tem 48 páginas para ler de um livro. Ele decide ler 6 páginas por dia, todos os dias, sem parar. Quantos dias Matias levará para terminar a leitura?",
        "alternativas": {
            "A": "6",
            "B": "7",
            "C": "8",
            "D": "9",
            "E": "13"
        },
        "gabarito_correto": "C",
        "comentario_ia": "Para calcular o número de dias, divide-se o total de páginas pelo número de páginas lidas por dia. 48 páginas / 6 páginas/dia = 8 dias. Portanto, Matias levará 8 dias para terminar a leitura."
    },
    {
        "id": "2063187",
        "enunciado": "Um cano de esgoto tem 18 metros de comprimento e precisa ser dividido em 4 partes iguais. Qual é o comprimento de cada parte?",
        "alternativas": {
            "A": "3,0 metros",
            "B": "4,5 metros",
            "C": "2,0 metros",
            "D": "5,5 metros"
        },
        "gabarito_correto": "B",
        "comentario_ia": "Para dividir 18 metros em 4 partes iguais, basta realizar a operação 18 / 4, que resulta em 4,5 metros para cada parte."
    },
    {
        "id": "2033611",
        "enunciado": "Um motorista precisa dividir igualmente uma carga de 1500 kg entre 5 caminhões. Quantos quilogramas de carga cada caminhão deverá transportar?",
        "alternativas": {
            "A": "250 kg.",
            "B": "300 kg.",
            "C": "350 kg.",
            "D": "400 kg."
        },
        "gabarito_correto": "B",
        "comentario_ia": "Para dividir igualmente 1500 kg entre 5 caminhões, basta realizar a operação de divisão: 1500 kg / 5 caminhões = 300 kg por caminhão."
    },
    {
        "id": "2199375",
        "enunciado": "Antônio possui 45 livros e pretende organizá-los em 3 prateleiras de modo que todas as prateleiras tenham a mesma quantidade de livros. Portanto, pode-se dizer que a quantidade total de livros em cada prateleira será igual a:",
        "alternativas": {
            "A": "15",
            "B": "14",
            "C": "13",
            "D": "12"
        },
        "gabarito_correto": "A",
        "comentario_ia": "O calculo para determinar a quantidade de livros em cada prateleira consiste em dividir o total de livros (45) pelo numero de prateleiras (3), resultando em 15 livros por prateleira."
    },
    {
        "id": "1011940",
        "enunciado": "Ana comprou 51 chocolates e deseja distribuí-los entre seus 3 netos. Sabendo-se que todos receberão a mesma quantidade, ao todo, quantos chocolates cada neto receberá?",
        "alternativas": {
            "A": "16",
            "B": "17",
            "C": "18",
            "D": "19"
        },
        "gabarito_correto": "B",
        "comentario_ia": "Para saber quantos chocolates cada neto receberá, divida o total de chocolates pelo número de netos. 51 chocolates / 3 netos = 17 chocolates por neto. A divisão resulta em 17, que é a quantidade que cada neto receberá."
    },
    {
        "id": "2046491",
        "enunciado": "Um caminhão possui capacidade de carga de até 5.000 quilos. Qual é o maior número de caixas que ele pode transportar, se cada uma delas pesa 100 quilos?",
        "alternativas": {
            "A": "30.",
            "B": "40.",
            "C": "50.",
            "D": "60."
        },
        "gabarito_correto": "C",
        "comentario_ia": "Para calcular o número máximo de caixas, divida a capacidade total do caminhão pelo peso de cada caixa: 5000 kg / 100 kg/caixa = 50 caixas. Portanto, o caminhão pode transportar 50 caixas."
    },
    {
        "id": "2133749",
        "enunciado": "Gabriel fez um bolo e cortou em 16 fatias. Sabendo-se que ele tem que levar, para a escola, 128 fatias para uma festa, no mínimo, quantos bolos iguais ao anterior ele precisa fazer para conseguir as fatias a fim de levar para a escola?",
        "alternativas": {
            "A": "9",
            "B": "8",
            "C": "7",
            "D": "6"
        },
        "gabarito_correto": "B",
        "comentario_ia": "Para encontrar o número mínimo de bolos, divide-se o total de fatias necessárias (128) pelo número de fatias por bolo (16). 128 / 16 = 8. Portanto, Gabriel precisa fazer no mínimo 8 bolos."
    },
    {
        "id": "1189759",
        "enunciado": "Quatro estudantes de uma turma do ensino fundamental vão dividir igualmente entre eles a despesa que tiveram na compra de material para fazerem um trabalho da escola. Sabendo que o valor total da compra foi R$ 89,76, caberá a cada estudante a quantia de:",
        "alternativas": {
            "A": "R$ 22,44",
            "B": "R$ 21,40",
            "C": "R$ 20,44",
            "D": "R$ 21,45",
            "E": "R$ 20,24"
        },
        "gabarito_correto": "A",
        "comentario_ia": "Para dividir igualmente o valor da compra entre os 4 estudantes, basta dividir o valor total pela quantidade de estudantes. Valor por estudante = R$ 89,76 / 4 = R$ 22,44. A alternativa A apresenta o valor correto."
    },
    {
        "id": "2122664",
        "enunciado": "Se 10 rosas formam dois buquês de flores, é CORRETO afirmar que cada buquê possui exatamente:",
        "alternativas": {
            "A": "4 rosas.",
            "B": "5 rosas.",
            "C": "6 rosas.",
            "D": "10 rosas."
        },
        "gabarito_correto": "B",
        "comentario_ia": "Se 10 rosas formam dois buquês de forma igual, cada buquê terá 10 rosas / 2 buquês = 5 rosas por buquê. Logo, a alternativa B é a correta."
    },
    {
        "id": "1991828",
        "enunciado": "Um senhor combinou com o jornaleiro que pagaria adiantado e receberia sem custos seus jornais em casa. Cada exemplar custa R$ 1,25, o jornaleiro recebeu adiantado R$ 60,00, durante quantos dias o senhor receberá seu jornal em casa?",
        "alternativas": {
            "A": "40 dias.",
            "B": "44 dias.",
            "C": "48 dias.",
            "D": "52 dias."
        },
        "gabarito_correto": "C",
        "comentario_ia": "Para calcular o numero de dias, divida o valor total adiantado (R$ 60,00) pelo custo diario de cada jornal (R$ 1,25). 60,00 / 1,25 = 48. Portanto, o senhor recebera o jornal por 48 dias."
    },
    {
        "id": "1190105",
        "enunciado": "O quociente da divisão que tem como dividendo 3,25 e divisor 0,5 é igual a:",
        "alternativas": {
            "A": "6,5",
            "B": "0,65",
            "C": "0,065",
            "D": "0,0065",
            "E": "0,00065"
        },
        "gabarito_correto": "A",
        "comentario_ia": "Para dividir 3,25 por 0,5, pode-se multiplicar ambos os números por 10 para remover as vírgulas: 32,5 / 5. Realizando a divisão, o resultado é 6,5."
    },
    {
        "id": "2066076",
        "enunciado": "O Colégio “Albert Einstein”, promoveu uma gincana para arrecadação de leite em pó, que serão doados para as instituições assistenciais. Os alunos arrecadaram 840 latas de leite em pó. Para a doação, as latas de leite, foram embaladas em caixas contendo 30 latas cada uma. Quantas caixas serão necessárias para colocar o leite arrecadado para a doação?",
        "alternativas": {
            "A": "28 caixas.",
            "B": "31 caixas.",
            "C": "29 caixas.",
            "D": "30 caixas."
        },
        "gabarito_correto": "A",
        "comentario_ia": "Para calcular o número de caixas, basta dividir o total de latas de leite pela quantidade de latas por caixa: 840 latas / 30 latas/caixa = 28 caixas."
    }
]